typestry/__init__.py
typestry/py.typed
typestry-0.0.0.dev0.dist-info/METADATA
typestry-0.0.0.dev0.dist-info/WHEEL
typestry-0.0.0.dev0.dist-info/licenses/LICENSE.txt
typestry-0.0.0.dev0.dist-info/RECORD
