Metadata-Version: 2.4
Name: typestry
Version: 0.0.0.dev0
Summary: Tool to verify type checker behavior by ensuring failures occur when expected.
Author: Chris
License-File: LICENSE.txt
Requires-Python: >=3.12
